tree_sitter_ballerina/__init__.py
tree_sitter_ballerina/_binding.cpython-313-darwin.so
tree_sitter_ballerina-0.1.0.dist-info/licenses/LICENSE.md
tree_sitter_ballerina-0.1.0.dist-info/METADATA
tree_sitter_ballerina-0.1.0.dist-info/WHEEL
tree_sitter_ballerina-0.1.0.dist-info/top_level.txt
tree_sitter_ballerina-0.1.0.dist-info/RECORD
